csvformatmail/__init__.py
csvformatmail/_cli.py
csvformatmail/_version.py
csvformatmail/mail.py
csvformatmail-1.3.3.dist-info/licenses/LICENSE
csvformatmail-1.3.3.dist-info/METADATA
csvformatmail-1.3.3.dist-info/WHEEL
csvformatmail-1.3.3.dist-info/entry_points.txt
csvformatmail-1.3.3.dist-info/top_level.txt
csvformatmail-1.3.3.dist-info/RECORD
