Metadata-Version: 2.4
Name: csvformatmail
Version: 1.3.3
Summary: A tool to send many mails from csv and a template
Author-email: Jean-Benoist Leger <jbleger@hds.utc.fr>
Maintainer-email: Jean-Benoist Leger <jbleger@hds.utc.fr>
License: MIT License
Project-URL: homepage, https://gitlab.com/jbleger/csvformatmail
Classifier: License :: OSI Approved :: MIT License
Classifier: Development Status :: 3 - Alpha
Classifier: Programming Language :: Python
Requires-Python: >=3.10
License-File: LICENSE
Requires-Dist: argcomplete
Requires-Dist: csvspoon>=1.1.3
Requires-Dist: numpy
Requires-Dist: cryptography
Requires-Dist: jinja2
Dynamic: license-file
